ExploriPy/EDA.py
ExploriPy/FeatureType.py
ExploriPy/TargetAnalysisCategorical.py
ExploriPy/TargetAnalysisContinuous.py
ExploriPy/WOE_IV.py
ExploriPy/__init__.py
ExploriPy/test.py
ExploriPy/HTMLTemplate/dist/HTMLTemplate_V2.html
ExploriPy/HTMLTemplate/dist/HTMLTemplate_target_Categorical.html
ExploriPy/HTMLTemplate/dist/HTMLTemplate_target_Continuous.html
ExploriPy/HTMLTemplate/dist/assets/css/dashboard.css
ExploriPy/HTMLTemplate/dist/assets/css/dashboard.rtl.css
ExploriPy/HTMLTemplate/dist/assets/fonts/feather/feather-webfont.eot
ExploriPy/HTMLTemplate/dist/assets/fonts/feather/feather-webfont.svg
ExploriPy/HTMLTemplate/dist/assets/fonts/feather/feather-webfont.ttf
ExploriPy/HTMLTemplate/dist/assets/fonts/feather/feather-webfont.woff
ExploriPy/HTMLTemplate/dist/assets/image/binoculars.png
ExploriPy/HTMLTemplate/dist/assets/js/core.js
ExploriPy/HTMLTemplate/dist/assets/js/dashboard.js
ExploriPy/HTMLTemplate/dist/assets/js/require.min.js
ExploriPy/HTMLTemplate/dist/assets/js/vendors/bootstrap.bundle.min.js
ExploriPy/HTMLTemplate/dist/assets/js/vendors/chart.bundle.min.js
ExploriPy/HTMLTemplate/dist/assets/js/vendors/circle-progress.min.js
ExploriPy/HTMLTemplate/dist/assets/js/vendors/jquery-3.2.1.min.js
ExploriPy/HTMLTemplate/dist/assets/js/vendors/jquery-3.2.1.slim.min.js
ExploriPy/HTMLTemplate/dist/assets/js/vendors/jquery-jvectormap-2.0.3.min.js
ExploriPy/HTMLTemplate/dist/assets/js/vendors/jquery-jvectormap-de-merc.js
ExploriPy/HTMLTemplate/dist/assets/js/vendors/jquery-jvectormap-world-mill.js
ExploriPy/HTMLTemplate/dist/assets/js/vendors/jquery.sparkline.min.js
ExploriPy/HTMLTemplate/dist/assets/js/vendors/jquery.tablesorter.min.js
ExploriPy/HTMLTemplate/dist/assets/js/vendors/selectize.min.js
ExploriPy/HTMLTemplate/dist/assets/plugins/charts-c3/plugin.css
ExploriPy/HTMLTemplate/dist/assets/plugins/charts-c3/plugin.js
ExploriPy/HTMLTemplate/dist/assets/plugins/charts-c3/js/c3.min.js
ExploriPy/HTMLTemplate/dist/assets/plugins/charts-c3/js/d3.v3.min.js
ExploriPy-1.1.2.dist-info/LICENSE
ExploriPy-1.1.2.dist-info/METADATA
ExploriPy-1.1.2.dist-info/WHEEL
ExploriPy-1.1.2.dist-info/top_level.txt
ExploriPy-1.1.2.dist-info/RECORD
