Metadata-Version: 2.1
Name: ExploriPy
Version: 1.1.2
Summary: Pre-Modelling Analysis of the data by doing various exploratory data analysis and Statistical Test
Home-page: https://github.com/exploripy/exploripy
Author: Sajan Kumar Bhagat, Kunjithapatham Sivakumar, Shashank Shekhar
Author-email: bhagat.sajan0073@gmail.com, s.vibish@gmail.com, quintshekhar@gmail.com
Maintainer: Sajan Kumar Bhagat, Kunjithapatham Sivakumar, Shashank Shekhar
Maintainer-email: bhagat.sajan0073@gmail.com, s.vibish@gmail.com, quintshekhar@gmail.com
License: MIT
Platform: UNKNOWN
Requires-Dist: pandas
Requires-Dist: numpy
Requires-Dist: Jinja2
Requires-Dist: scipy
Requires-Dist: seaborn
Requires-Dist: matplotlib
Requires-Dist: statsmodels
Requires-Dist: sklearn
Requires-Dist: tqdm
